assignment1/q3_up_counter/modcounter.v
module modcounter(clk,rst,ctrl,data,count);
   
  input clk,rst;
  input [2:0] ctrl;  // to decide what the counter must do
  input [3:0] data;
  output reg [3:0] count;
  reg flag;   // register variable to keep track of whether up count or down count needs to be performed
  parameter N = 7;  // N can go up to 16 
  
  always@(posedge clk)
    begin
           if(rst  == 1'b1)   
             begin
                count <= 4'b0000;                                // rst  = 1 => Local Synchronous reset
                flag  <= 0;                                      // flag = 0 => Indicates Up Counting
             end
      else if(ctrl == 3'b000) count <= count;                    // ctrl = 0 => hold previous value
      else if(ctrl == 3'b001) count <= (count+1)%N;              // ctrl = 1 => up count
      else if(ctrl == 3'b010)                                    // ctrl = 2 => down count
          begin
             if(count == 4'b0000)   count <= N-1;
             else                   count <= count-1;
          end
           
      else if(ctrl == 3'b011)                                    // ctrl = 3 => count up / down [first up and then down]
               begin
                 if(flag == 1'b0)                                // indicates up count (The x is for simulation purposes)
                    begin
                       if(count == N-1 )
                         begin  
                            flag  <= 1;                          // Max count is reached => Change the status of the flag to indicate 
                            count <= count - 1;                  // Decrement the count once for this clock cycle
                          end
                       else  count <= count + 1;                 // Max count is not yet reached => Continue up counting
                    end
                 
                 else                                            // flag = 1 indicates down count
                    begin
                       if(count == 0) 
                         begin
                           flag <= 0;                            // Min count is reached => Reset the flag
                           count = count + 1;                    // Increment the count once for this clock cycle
                         end
                       else count <= count - 1;                  // Min count is not yet reached => Continue down counting
                    end 
               end
           
      else if(ctrl == 3'b100) count <= data;                     // ctrl = 4 => load data
      else                    count <= count;                    // Just hold the data  for ctrl = 5,6,7
    end
endmodule

assignment1/q3_up_counter/modcounter_tb.v
module modcounter_tb;
  reg clk,rst;
  reg [2:0] ctrl;
  reg [3:0] data;
  wire [3:0] count;
  modcounter m1(.clk(clk), .rst(rst), .ctrl(ctrl), .data(data), .count(count));
  always #2 clk = ~clk;
  
  initial 
    begin
       $dumpfile("modcounter_waveforms.vcd");
       $dumpvars(0,modcounter_tb);
       clk = 1'b0;
       $monitor($time," rst = %b, ctrl = %b,count = %b ",rst,ctrl,count);
       #5   rst = 1'b1; ctrl = 3'b000 ; data = 4'h4;
       #5   rst = 1'b0; ctrl = 3'b001 ; data = 4'h4;
       #5   rst = 1'b0; ctrl = 3'b001 ; data = 4'h4;
       #5   rst = 1'b0; ctrl = 3'b001 ; data = 4'h4;
       #5   rst = 1'b0; ctrl = 3'b011 ; data = 4'h4;
       #5   rst = 1'b0; ctrl = 3'b011 ; data = 4'h4;
       #5   rst = 1'b0; ctrl = 3'b011 ; data = 4'h4;
       #5   rst = 1'b0; ctrl = 3'b011 ; data = 4'h4;
       #5   rst = 1'b0; ctrl = 3'b011 ; data = 4'h4;
       #5   rst = 1'b0; ctrl = 3'b011 ; data = 4'h4;
       #5   rst = 1'b0; ctrl = 3'b011 ; data = 4'h4;
       #5   rst = 1'b1; ctrl = 3'b010 ; data = 4'h4;
       #5   rst = 1'b0; ctrl = 3'b010 ; data = 4'h4;
       #5   rst = 1'b0; ctrl = 3'b010 ; data = 4'h4;
       #5   rst = 1'b0; ctrl = 3'b011 ; data = 4'h4;
       #5   rst = 1'b0; ctrl = 3'b011 ; data = 4'h4;
       #5   rst = 1'b0; ctrl = 3'b011 ; data = 4'h4;
       #5   rst = 1'b0; ctrl = 3'b011 ; data = 4'h4;
       #5   $finish;
    end
endmodule

assignment1/q3_up_counter/modcounter_waveforms.vcd
$date
	Sat Jan 27 14:21:09 2024
$end
$version
	Icarus Verilog
$end
$timescale
	1s
$end
$scope module modcounter_tb $end
$var wire 4 ! count [3:0] $end
$var reg 1 " clk $end
$var reg 3 # ctrl [2:0] $end
$var reg 4 $ data [3:0] $end
$var reg 1 % rst $end
$scope module m1 $end
$var wire 1 " clk $end
$var wire 3 & ctrl [2:0] $end
$var wire 4 ' data [3:0] $end
$var wire 1 % rst $end
$var reg 4 ( count [3:0] $end
$var reg 1 ) flag $end
$upscope $end
$upscope $end
$enddefinitions $end
#0
$dumpvars
x)
bx (
bx '
bx &
x%
bx $
bx #
0"
bx !
$end
#2
1"
#4
0"
#5
b100 $
b100 '
b0 #
b0 &
1%
#6
0)
b0 !
b0 (
1"
#8
0"
#10
b1 !
b1 (
1"
b1 #
b1 &
0%
#12
0"
#14
b10 !
b10 (
1"
#16
0"
#18
b11 !
b11 (
1"
#20
0"
#22
b100 !
b100 (
1"
#24
0"
#25
b11 #
b11 &
#26
b101 !
b101 (
1"
#28
0"
#30
b110 !
b110 (
1"
#32
0"
#34
b101 !
b101 (
1)
1"
#36
0"
#38
b100 !
b100 (
1"
#40
0"
#42
b11 !
b11 (
1"
#44
0"
#46
b10 !
b10 (
1"
#48
0"
#50
b1 !
b1 (
1"
#52
0"
#54
b0 !
b0 (
1"
#56
0"
#58
0)
b1 !
b1 (
1"
#60
0"
b10 #
b10 &
1%
#62
b0 !
b0 (
1"
#64
0"
#65
0%
#66
b110 !
b110 (
1"
#68
0"
#70
b101 !
b101 (
1"
#72
0"
#74
b100 !
b100 (
1"
#75
b11 #
b11 &
#76
0"
#78
b101 !
b101 (
1"
#80
0"
#82
b110 !
b110 (
1"
#84
0"
#86
b101 !
b101 (
1)
1"
#88
0"
#90
b100 !
b100 (
1"
#92
0"
#94
b11 !
b11 (
1"
