assignment1/q3_up_counter/modcounter.v
module modcounter(clk,ctrl,data,count);
   
  input clk;
  input [2:0] ctrl;  // to decide what the counter must do
  input [3:0] data;
  output reg [3:0] count;
  reg flag;   // register variable to keep track of whether up count or down count needs to be performed
  parameter N = 7;  // N can go up to 16 
  
  initial  flag  = 0; // flag initialized to 1 to indicate up count  (only for simulation)
  
  always@(posedge clk)
    begin
           if(ctrl == 3'b000) count <= 4'b0000;                  // ctrl = 0 => Local Synchronous reset
      else if(ctrl == 3'b001) count <= count;                    // ctrl = 1 => hold previous value
      else if(ctrl == 3'b010) count <= (count+1)%N;              // ctrl = 2 => up count
      else if(ctrl == 3'b011) count <= count-1;                  // ctrl = 3 => down count
           
      else if(ctrl == 3'b100)                                    // ctrl = 4 => count up / down [first up and then down]
               begin
                 if(flag == 1'b0)                                // indicates up count (The x is for simulation purposes)
                    begin
                       if(count == N-1 )
                         begin  
                            flag  <= 1;                          // Max count is reached => Change the status of the flag to indicate 
                            count <= count - 1;                  // Decrement the count once for this clock cycle
                          end
                       else  count <= count + 1;                 // Max count is not yet reached => Continue up counting
                    end
                 
                 else                                            // flag = 1 indicates down count
                    begin
                       if(count == 0) 
                         begin
                           flag <= 0;                            // Min count is reached => Reset the flag
                           count = count + 1;                    // Increment the count once for this clock cycle
                         end
                       else count <= count - 1;                  // Min count is not yet reached => Continue down counting
                    end 
               end
           
      else if(ctrl == 3'b101) count <= data;                     // ctrl = 5 => load data
      else                    count <= count;                    // Just hold the data  for ctrl = 6,7
    end
endmodule

assignment1/q3_up_counter/modcounter_tb.v
module modcounter_tb;
  reg clk;
  reg [2:0] ctrl;
  reg [3:0] data;
  wire [3:0] count;
  modcounter m1(.clk(clk), .ctrl(ctrl), .data(data), .count(count));
  always #2 clk = ~clk;
  
  initial 
    begin
       $dumpfile("modcounter_waveforms.vcd");
       $dumpvars(0,modcounter_tb);
       clk = 1'b0;
       $monitor($time," ctrl = %b,count = %b ",ctrl,count);
       #5   ctrl = 3'b000 ; data = 4'h4;
       #5   ctrl = 3'b010 ; data = 4'h4;
       #5   ctrl = 3'b010 ; data = 4'h4;
       #5   ctrl = 3'b100 ; data = 4'h4;
       #5   ctrl = 3'b100 ; data = 4'h4;
       #5   ctrl = 3'b100 ; data = 4'h4;
       #5   ctrl = 3'b100 ; data = 4'h4;
       #5   ctrl = 3'b100 ; data = 4'h4;
       #5   ctrl = 3'b100 ; data = 4'h4;
       #5   ctrl = 3'b100 ; data = 4'h4;
       #5   ctrl = 3'b100 ; data = 4'h4;
       #5   ctrl = 3'b100 ; data = 4'h4;
       #5   ctrl = 3'b100 ; data = 4'h4;
       #5   ctrl = 3'b100 ; data = 4'h4;
       #5   ctrl = 3'b100 ; data = 4'h4;
       #5   ctrl = 3'b100 ; data = 4'h4;
       #5   ctrl = 3'b100 ; data = 4'h4;
       #5   ctrl = 3'b100 ; data = 4'h4;
       #5   $finish;
    end
endmodule

assignment1/q3_up_counter/modcounter_waveforms.vcd
$date
	Fri Jan 26 21:27:37 2024
$end
$version
	Icarus Verilog
$end
$timescale
	1s
$end
$scope module modcounter_tb $end
$var wire 4 ! count [3:0] $end
$var reg 1 " clk $end
$var reg 3 # ctrl [2:0] $end
$var reg 4 $ data [3:0] $end
$scope module m1 $end
$var wire 1 " clk $end
$var wire 3 % ctrl [2:0] $end
$var wire 4 & data [3:0] $end
$var reg 4 ' count [3:0] $end
$var reg 1 ( flag $end
$upscope $end
$upscope $end
$enddefinitions $end
#0
$dumpvars
0(
bx '
bx &
bx %
bx $
bx #
0"
bx !
$end
#2
1"
#4
0"
#5
b100 $
b100 &
b0 #
b0 %
#6
b0 !
b0 '
1"
#8
0"
#10
b1 !
b1 '
1"
b10 #
b10 %
#12
0"
#14
b10 !
b10 '
1"
#16
0"
#18
b11 !
b11 '
1"
#20
0"
b100 #
b100 %
#22
b100 !
b100 '
1"
#24
0"
#26
b101 !
b101 '
1"
#28
0"
#30
b110 !
b110 '
1"
#32
0"
#34
b101 !
b101 '
1(
1"
#36
0"
#38
b100 !
b100 '
1"
#40
0"
#42
b11 !
b11 '
1"
#44
0"
#46
b10 !
b10 '
1"
#48
0"
#50
b1 !
b1 '
1"
#52
0"
#54
b0 !
b0 '
1"
#56
0"
#58
0(
b1 !
b1 '
1"
#60
0"
#62
b10 !
b10 '
1"
#64
0"
#66
b11 !
b11 '
1"
#68
0"
#70
b100 !
b100 '
1"
#72
0"
#74
b101 !
b101 '
1"
#76
0"
#78
b110 !
b110 '
1"
#80
0"
#82
b101 !
b101 '
1(
1"
#84
0"
#86
b100 !
b100 '
1"
#88
0"
#90
b11 !
b11 '
1"
#92
0"
#94
b10 !
b10 '
1"
