FPGA_Practise_Codes/shift_register/shift_register.v
module shift_register(data,rst,clk,result);
  input data,rst,clk;
  output reg [3:0] result;   // register to hold the output values
  reg qa, qb, qc, qd;
  
  
  always@(*)
     begin
        result[3:0] = {qa,qb,qc,qd};
     end
     
    
  always@(posedge clk)
    begin
      if(rst == 0) 
         begin
            qa <= 1'b0;     // Good practice to use Non Blocking assignments inside clocked always blocks
            qb <= 1'b0;
            qc <= 1'b0;
            qd <= 1'b0;
         end
       
       else
          begin
            qa <= data;
            qb <= qa;
            qc <= qb;
            qd <= qc;
          end
    end
endmodule

FPGA_Practise_Codes/shift_register/shift_register_tb.v
module shift_register_tb;
reg data,clk,rst;  // Inputs to be given to DUT are declared as registers as they will be initialized values in "initial" blocks
wire [3:0]result;  // These wires will be continuously driven by the output of DUT

shift_register G(.data(data) , .clk(clk) , .rst(rst) , .result(result));  // Module Instantiation

always #2 clk = ~clk;

initial 
  begin
    $monitor ("Time=%d, data = %b, result = %b ",$time,data,result);
    $dumpfile("shift_register_simulation.vcd");
    $dumpvars(0,shift_register_tb);
    #0  clk  = 1'b1; rst  = 1'b0; data = 1'b0 ;
    #2  rst  = 1'b1;
    #5  data = 1'b1;
    #10 data = 1'b0;
    #50 $finish;
  end
endmodule

FPGA_Practise_Codes/shift_register/shift_register_simulation.vcd
$date
	Tue Feb 27 07:20:19 2024
$end
$version
	Icarus Verilog
$end
$timescale
	1s
$end
$scope module shift_register_tb $end
$var wire 4 ! result [3:0] $end
$var reg 1 " clk $end
$var reg 1 # data $end
$var reg 1 $ rst $end
$scope module G $end
$var wire 1 " clk $end
$var wire 1 # data $end
$var wire 1 $ rst $end
$var reg 1 % qa $end
$var reg 1 & qb $end
$var reg 1 ' qc $end
$var reg 1 ( qd $end
$var reg 4 ) result [3:0] $end
$upscope $end
$upscope $end
$enddefinitions $end
#0
$dumpvars
b0 )
0(
0'
0&
0%
0$
0#
1"
b0 !
$end
#2
1$
0"
#4
1"
#6
0"
#7
1#
#8
b1000 !
b1000 )
1%
1"
#10
0"
#12
b1100 !
b1100 )
1&
1"
#14
0"
#16
b1110 !
b1110 )
1'
1"
#17
0#
#18
0"
#20
b111 !
b111 )
1(
0%
1"
#22
0"
#24
b11 !
b11 )
0&
1"
#26
0"
#28
b1 !
b1 )
0'
1"
#30
0"
#32
b0 !
b0 )
0(
1"
